youtubeaio/__init__.py
youtubeaio/const.py
youtubeaio/helper.py
youtubeaio/models.py
youtubeaio/oauth.py
youtubeaio/py.typed
youtubeaio/types.py
youtubeaio/youtube.py
youtubeaio_extended-1.2.2.dist-info/LICENSE.md
youtubeaio_extended-1.2.2.dist-info/METADATA
youtubeaio_extended-1.2.2.dist-info/WHEEL
youtubeaio_extended-1.2.2.dist-info/RECORD
